docassemble/GithubFeedbackForm/__init__.py
docassemble/GithubFeedbackForm/alembic.ini
docassemble/GithubFeedbackForm/feedback_on_server.py
docassemble/GithubFeedbackForm/github_issue.py
docassemble/GithubFeedbackForm/requirements.txt
docassemble/GithubFeedbackForm/test_feedback_db.py
docassemble/GithubFeedbackForm/alembic/README
docassemble/GithubFeedbackForm/alembic/env.py
docassemble/GithubFeedbackForm/alembic/script.py.mako
docassemble/GithubFeedbackForm/alembic/versions/542797f969ea_initial_alembic_migration.py
docassemble/GithubFeedbackForm/alembic/versions/5b46c3a6f9b7_add_github_user_and_repo.py
docassemble/GithubFeedbackForm/alembic/versions/8821926028d6_archiving.py
docassemble/GithubFeedbackForm/data/questions/browse_feedback_sessions.yml
docassemble/GithubFeedbackForm/data/questions/embedded_review.yml
docassemble/GithubFeedbackForm/data/questions/feedback.yml
docassemble/GithubFeedbackForm/data/sources/README.md
docassemble/GithubFeedbackForm/data/static/README.md
docassemble/GithubFeedbackForm/data/static/bug.svg
docassemble/GithubFeedbackForm/data/static/confusion.svg
docassemble/GithubFeedbackForm/data/static/enhance.svg
docassemble/GithubFeedbackForm/data/static/lifebuoy.svg
docassemble/GithubFeedbackForm/data/static/love.svg
docassemble/GithubFeedbackForm/data/static/opinion.svg
docassemble/GithubFeedbackForm/data/templates/README.md
docassemble_githubfeedbackform-0.5.5.dist-info/licenses/LICENSE
docassemble_githubfeedbackform-0.5.5.dist-info/METADATA
docassemble_githubfeedbackform-0.5.5.dist-info/WHEEL
docassemble_githubfeedbackform-0.5.5.dist-info/top_level.txt
docassemble_githubfeedbackform-0.5.5.dist-info/RECORD
