Metadata-Version: 2.4
Name: docassemble.GithubFeedbackForm
Version: 0.5.5
Summary: Integration of GitHub issues with Docassemble interviews for collecting user feedback
Home-page: https://courtformsonline.org
Author: Quinten Steenhuis
Author-email: qsteenhuis@suffolk.edu
License: The MIT License (MIT)
License-File: LICENSE
Requires-Dist: docassemble.ALToolbox>=0.6.0
Requires-Dist: google-generativeai
Dynamic: author
Dynamic: author-email
Dynamic: description
Dynamic: description-content-type
Dynamic: home-page
Dynamic: license
Dynamic: license-file
Dynamic: requires-dist
Dynamic: summary
